polars_utils/__init__.py
polars_utils/covariance.py
polars_utils/fixed_effects.py
polars_utils/quantile.py
polars_utils/shrinkage.py
polars_utils/smoothing.py
polars_utils/stats.py
polars_utils/weights.py
polars_utils-0.1.16.dist-info/METADATA
polars_utils-0.1.16.dist-info/WHEEL
polars_utils-0.1.16.dist-info/RECORD
