Metadata-Version: 2.4
Name: polars-utils
Version: 0.1.16
Summary: Weighted means, variances, quantiles, fixed effects, and more in Polars.
Author-email: Alistair Pattison <alistairpattison@gmail.com>
Requires-Python: >=3.13
Requires-Dist: polars>=1.24.0
Requires-Dist: rpy2>=3.5.17
Requires-Dist: tqdm>=4.67.1
